[{"iata_from":"AKN","routes":[{"first_flight":"2018-02-14","common_duration":"65","iata_from":"AKN","iata_to":"ANC","id":1123,"city_name_en":"Anchorage","is_new":"0","filtered_out":0,"airlineroutes":[{"carrier":"7H","carrier_name":"Ravn Alaska","first_flight":"2020-06-01","last_flight":"2022-11-13","common_duration":"65","route_id":"1123","is_new":"0"},{"carrier":"AS","carrier_name":"Alaska Airlines","first_flight":"2020-05-21","last_flight":"2020-08-17","common_duration":"55","route_id":"1123","is_new":"0"}]},{"first_flight":"2018-02-14","common_duration":"30","iata_from":"AKN","iata_to":"DLG","id":1124,"city_name_en":"Dillingham","is_new":"0","filtered_out":0,"airlineroutes":[{"carrier":"7H","carrier_name":"Ravn Alaska","first_flight":null,"last_flight":"2022-11-12","common_duration":"30","route_id":"1124","is_new":"0"}]}]}]