[{"iata_from":"AVN","routes":[{"first_flight":"2018-05-26","common_duration":"130","iata_from":"AVN","iata_to":"BHX","id":2962,"city_name_en":"Birmingham","is_new":"0","filtered_out":0,"airlineroutes":[{"carrier":"BE","carrier_name":"Flybe","first_flight":"2020-07-04","last_flight":"2020-08-29","common_duration":"130","route_id":"2962","is_new":"0"}]},{"first_flight":"2018-05-26","common_duration":"130","iata_from":"AVN","iata_to":"SOU","id":2963,"city_name_en":"Southampton","is_new":"0","filtered_out":0,"airlineroutes":[{"carrier":"BE","carrier_name":"Flybe","first_flight":"2020-07-04","last_flight":"2020-08-29","common_duration":"130","route_id":"2963","is_new":"0"}]}]}]