[{"iata_from":"DCA","routes":[{"first_flight":null,"common_duration":"78","iata_from":"DCA","iata_to":"CAK","id":11546,"city_name_en":"Akron","is_new":"0","filtered_out":0,"airlineroutes":[{"carrier":"AA","carrier_name":"American Airlines","first_flight":null,"last_flight":"2022-11-18","common_duration":"78","route_id":"11546","is_new":"0"}]},{"first_flight":null,"common_duration":"83","iata_from":"DCA","iata_to":"ALB","id":11533,"city_name_en":"Albany","is_new":"0","filtered_out":0,"airlineroutes":[{"carrier":"AA","carrier_name":"American Airlines","first_flight":null,"last_flight":"2022-11-18","common_duration":"83","route_id":"11533","is_new":"0"}]},{"first_flight":null,"common_duration":"119","iata_from":"DCA","iata_to":"ATL","id":11534,"city_name_en":"Atlanta","is_new":"0","filtered_out":0,"airlineroutes":[{"carrier":"AA","carrier_name":"American Airlines","first_flight":null,"last_flight":"2022-11-18","common_duration":"124","route_id":"11534","is_new":"0"},{"carrier":"DL","carrier_name":"Delta Air Lines","first_flight":null,"last_flight":"2022-11-13","common_duration":"119","route_id":"11534","is_new":"0"},{"carrier":"WN","carrier_name":"Southwest Airlines","first_flight":null,"last_flight":"2020-06-06","common_duration":"120","route_id":"11534","is_new":"0"}]},{"first_flight":"2019-04-08","common_duration":"105","iata_from":"DCA","iata_to":"AGS","id":52362,"city_name_en":"Augusta","is_new":"0","filtered_out":0,"airlineroutes":[{"carrier":"AA","carrier_name":"American Airlines","first_flight":null,"last_flight":"2022-11-12","common_duration":"105","route_id":"52362","is_new":"0"}]},{"first_flight":null,"common_duration":"230","iata_from":"DCA","iata_to":"AUS","id":11535,"city_name_en":"Austin","is_new":"0","filtered_out":0,"airlineroutes":[{"carrier":"WN","carrier_name":"Southwest Airlines","first_flight":null,"last_flight":"2020-06-06","common_duration":"230","route_id":"11535","is_new":"0"}]},{"first_flight":null,"common_duration":"108","iata_from":"DCA","iata_to":"BGR","id":11538,"city_name_en":"Bangor","is_new":"0","filtered_out":0,"airlineroutes":[{"carrier":"AA","carrier_name":"American Airlines","first_flight":null,"last_flight":"2022-11-12","common_duration":"108","route_id":"11538","is_new":"0"}]},{"first_flight":"2019-02-03","common_duration":"150","iata_from":"DCA","iata_to":"BTR","id":11542,"city_name_en":"Baton Rouge","is_new":"0","filtered_out":0,"airlineroutes":[{"carrier":"UA","carrier_name":"United Airlines","first_flight":null,"last_flight":"2020-01-26","common_duration":"150","route_id":"11542","is_new":"0"}]},{"first_flight":null,"common_duration":"181","iata_from":"DCA","iata_to":"XNA","id":11622,"city_name_en":"Bentonville","is_new":"0","filtered_out":0,"airlineroutes":[{"carrier":"AA","carrier_name":"American Airlines","first_flight":null,"last_flight":"2022-11-18","common_duration":"181","route_id":"11622","is_new":"0"}]},{"first_flight":null,"common_duration":"131","iata_from":"DCA","iata_to":"BHM","id":11539,"city_name_en":"Birmingham","is_new":"0","filtered_out":0,"airlineroutes":[{"carrier":"AA","carrier_name":"American Airlines","first_flight":null,"last_flight":"2022-11-18","common_duration":"131","route_id":"11539","is_new":"0"}]},{"first_flight":"2019-09-09","common_duration":"95","iata_from":"DCA","iata_to":"BOS","id":11541,"city_name_en":"Boston","is_new":"0","filtered_out":0,"airlineroutes":[{"carrier":"AA","carrier_name":"American Airlines","first_flight":null,"last_flight":"2022-11-18","common_duration":"95","route_id":"11541","is_new":"0"},{"carrier":"B6","carrier_name":"JetBlue Airways","first_flight":null,"last_flight":"2022-03-25","common_duration":"91","route_id":"11541","is_new":"0"},{"carrier":"DL","carrier_name":"Delta Air Lines","first_flight":null,"last_flight":"2022-11-12","common_duration":"104","route_id":"11541","is_new":"0"}]},{"first_flight":null,"common_duration":"79","iata_from":"DCA","iata_to":"BUF","id":11544,"city_name_en":"Buffalo","is_new":"0","filtered_out":0,"airlineroutes":[{"carrier":"AA","carrier_name":"American Airlines","first_flight":null,"last_flight":"2022-11-18","common_duration":"79","route_id":"11544","is_new":"0"}]},{"first_flight":null,"common_duration":"96","iata_from":"DCA","iata_to":"BTV","id":11543,"city_name_en":"Burlington","is_new":"0","filtered_out":0,"airlineroutes":[{"carrier":"AA","carrier_name":"American Airlines","first_flight":null,"last_flight":"2022-11-18","common_duration":"96","route_id":"11543","is_new":"0"}]},{"first_flight":null,"common_duration":"71","iata_from":"DCA","iata_to":"CRW","id":11552,"city_name_en":"Charleston","is_new":"0","filtered_out":0,"airlineroutes":[{"carrier":"AA","carrier_name":"American Airlines","first_flight":null,"last_flight":"2022-11-12","common_duration":"71","route_id":"11552","is_new":"0"}]},{"first_flight":null,"common_duration":"103","iata_from":"DCA","iata_to":"CHS","id":11548,"city_name_en":"Charleston","is_new":"0","filtered_out":0,"airlineroutes":[{"carrier":"AA","carrier_name":"American Airlines","first_flight":null,"last_flight":"2022-11-13","common_duration":"103","route_id":"11548","is_new":"0"}]},{"first_flight":null,"common_duration":"100","iata_from":"DCA","iata_to":"CLT","id":11550,"city_name_en":"Charlotte","is_new":"0","filtered_out":0,"airlineroutes":[{"carrier":"AA","carrier_name":"American Airlines","first_flight":null,"last_flight":"2022-11-18","common_duration":"100","route_id":"11550","is_new":"0"}]},{"first_flight":null,"common_duration":"115","iata_from":"DCA","iata_to":"CHA","id":11547,"city_name_en":"Chattanooga","is_new":"0","filtered_out":0,"airlineroutes":[{"carrier":"AA","carrier_name":"American Airlines","first_flight":null,"last_flight":"2022-11-12","common_duration":"115","route_id":"11547","is_new":"0"}]},{"first_flight":null,"common_duration":"125","iata_from":"DCA","iata_to":"MDW","id":11583,"city_name_en":"Chicago","is_new":"0","filtered_out":0,"airlineroutes":[{"carrier":"WN","carrier_name":"Southwest Airlines","first_flight":null,"last_flight":"2020-06-06","common_duration":"125","route_id":"11583","is_new":"0"}]},{"first_flight":null,"common_duration":"136","iata_from":"DCA","iata_to":"ORD","id":11596,"city_name_en":"Chicago","is_new":"0","filtered_out":0,"airlineroutes":[{"carrier":"AA","carrier_name":"American Airlines","first_flight":null,"last_flight":"2022-11-18","common_duration":"137","route_id":"11596","is_new":"0"},{"carrier":"UA","carrier_name":"United Airlines","first_flight":null,"last_flight":"2022-11-18","common_duration":"135","route_id":"11596","is_new":"0"}]},{"first_flight":null,"common_duration":"100","iata_from":"DCA","iata_to":"CVG","id":11553,"city_name_en":"Cincinnati","is_new":"0","filtered_out":0,"airlineroutes":[{"carrier":"AA","carrier_name":"American Airlines","first_flight":null,"last_flight":"2022-11-12","common_duration":"99","route_id":"11553","is_new":"0"},{"carrier":"DL","carrier_name":"Delta Air Lines","first_flight":null,"last_flight":"2022-03-25","common_duration":"101","route_id":"11553","is_new":"0"}]},{"first_flight":null,"common_duration":"86","iata_from":"DCA","iata_to":"CLE","id":11549,"city_name_en":"Cleveland","is_new":"0","filtered_out":0,"airlineroutes":[{"carrier":"AA","carrier_name":"American Airlines","first_flight":null,"last_flight":"2022-11-18","common_duration":"86","route_id":"11549","is_new":"0"},{"carrier":"UA","carrier_name":"United Airlines","first_flight":null,"last_flight":"2022-11-18","common_duration":"86","route_id":"11549","is_new":"0"}]},{"first_flight":null,"common_duration":"93","iata_from":"DCA","iata_to":"CAE","id":11545,"city_name_en":"Columbia","is_new":"0","filtered_out":0,"airlineroutes":[{"carrier":"AA","carrier_name":"American Airlines","first_flight":null,"last_flight":"2022-11-12","common_duration":"93","route_id":"11545","is_new":"0"}]},{"first_flight":null,"common_duration":"87","iata_from":"DCA","iata_to":"CMH","id":11551,"city_name_en":"Columbus","is_new":"0","filtered_out":0,"airlineroutes":[{"carrier":"AA","carrier_name":"American Airlines","first_flight":null,"last_flight":"2022-11-18","common_duration":"89","route_id":"11551","is_new":"0"},{"carrier":"WN","carrier_name":"Southwest Airlines","first_flight":null,"last_flight":"2020-06-06","common_duration":"80","route_id":"11551","is_new":"0"}]},{"first_flight":null,"common_duration":"214","iata_from":"DCA","iata_to":"DFW","id":11557,"city_name_en":"Dallas","is_new":"0","filtered_out":0,"airlineroutes":[{"carrier":"AA","carrier_name":"American Airlines","first_flight":null,"last_flight":"2022-11-18","common_duration":"214","route_id":"11557","is_new":"0"}]},{"first_flight":"2018-02-16","common_duration":"205","iata_from":"DCA","iata_to":"DAL","id":11554,"city_name_en":"Dallas","is_new":"0","filtered_out":0,"airlineroutes":[{"carrier":"WN","carrier_name":"Southwest Airlines","first_flight":null,"last_flight":"2020-06-06","common_duration":"205","route_id":"11554","is_new":"0"}]},{"first_flight":null,"common_duration":"95","iata_from":"DCA","iata_to":"DAY","id":11555,"city_name_en":"Dayton","is_new":"0","filtered_out":0,"airlineroutes":[{"carrier":"AA","carrier_name":"American Airlines","first_flight":null,"last_flight":"2022-11-18","common_duration":"95","route_id":"11555","is_new":"0"}]},{"first_flight":null,"common_duration":"260","iata_from":"DCA","iata_to":"DEN","id":11556,"city_name_en":"Denver","is_new":"0","filtered_out":0,"airlineroutes":[{"carrier":"F9","carrier_name":"Frontier Airlines","first_flight":null,"last_flight":"2022-03-20","common_duration":"260","route_id":"11556","is_new":"0"},{"carrier":"UA","carrier_name":"United Airlines","first_flight":null,"last_flight":"2022-11-12","common_duration":"256","route_id":"11556","is_new":"0"}]},{"first_flight":"2020-02-01","common_duration":"169","iata_from":"DCA","iata_to":"DSM","id":11558,"city_name_en":"Des Moines","is_new":"0","filtered_out":0,"airlineroutes":[{"carrier":"AA","carrier_name":"American Airlines","first_flight":null,"last_flight":"2022-11-18","common_duration":"169","route_id":"11558","is_new":"0"},{"carrier":"UA","carrier_name":"United Airlines","first_flight":null,"last_flight":"2020-02-01","common_duration":"165","route_id":"11558","is_new":"1"}]},{"first_flight":"2019-12-14","common_duration":"99","iata_from":"DCA","iata_to":"DTW","id":11559,"city_name_en":"Detroit","is_new":"0","filtered_out":0,"airlineroutes":[{"carrier":"AA","carrier_name":"American Airlines","first_flight":null,"last_flight":"2022-11-18","common_duration":"102","route_id":"11559","is_new":"0"},{"carrier":"DL","carrier_name":"Delta Air Lines","first_flight":null,"last_flight":"2022-11-12","common_duration":"98","route_id":"11559","is_new":"0"}]},{"first_flight":null,"common_duration":"77","iata_from":"DCA","iata_to":"RDU","id":11606,"city_name_en":"Durham","is_new":"0","filtered_out":0,"airlineroutes":[{"carrier":"AA","carrier_name":"American Airlines","first_flight":null,"last_flight":"2022-11-18","common_duration":"77","route_id":"11606","is_new":"0"},{"carrier":"DL","carrier_name":"Delta Air Lines","first_flight":null,"last_flight":"2022-03-25","common_duration":"76","route_id":"11606","is_new":"0"}]},{"first_flight":null,"common_duration":"163","iata_from":"DCA","iata_to":"FLL","id":11562,"city_name_en":"Fort Lauderdale","is_new":"0","filtered_out":0,"airlineroutes":[{"carrier":"B6","carrier_name":"JetBlue Airways","first_flight":null,"last_flight":"2022-03-25","common_duration":"161","route_id":"11562","is_new":"0"},{"carrier":"WN","carrier_name":"Southwest Airlines","first_flight":null,"last_flight":"2020-06-06","common_duration":"170","route_id":"11562","is_new":"0"}]},{"first_flight":"2018-06-16","common_duration":"163","iata_from":"DCA","iata_to":"RSW","id":11608,"city_name_en":"Fort Myers","is_new":"0","filtered_out":0,"airlineroutes":[{"carrier":"AA","carrier_name":"American Airlines","first_flight":null,"last_flight":"2022-11-12","common_duration":"165","route_id":"11608","is_new":"0"},{"carrier":"B6","carrier_name":"JetBlue Airways","first_flight":null,"last_flight":"2022-03-19","common_duration":"162","route_id":"11608","is_new":"0"}]},{"first_flight":null,"common_duration":"119","iata_from":"DCA","iata_to":"GRR","id":11563,"city_name_en":"Grand Rapids","is_new":"0","filtered_out":0,"airlineroutes":[{"carrier":"AA","carrier_name":"American Airlines","first_flight":null,"last_flight":"2022-11-13","common_duration":"119","route_id":"11563","is_new":"0"}]},{"first_flight":null,"common_duration":"74","iata_from":"DCA","iata_to":"GSO","id":11564,"city_name_en":"Greensboro","is_new":"0","filtered_out":0,"airlineroutes":[{"carrier":"AA","carrier_name":"American Airlines","first_flight":null,"last_flight":"2022-11-18","common_duration":"74","route_id":"11564","is_new":"0"}]},{"first_flight":null,"common_duration":"96","iata_from":"DCA","iata_to":"GSP","id":11565,"city_name_en":"Greenville","is_new":"0","filtered_out":0,"airlineroutes":[{"carrier":"AA","carrier_name":"American Airlines","first_flight":null,"last_flight":"2022-11-13","common_duration":"96","route_id":"11565","is_new":"0"}]},{"first_flight":"2018-06-07","common_duration":"139","iata_from":"DCA","iata_to":"BDA","id":11536,"city_name_en":"Hamilton","is_new":"0","filtered_out":0,"airlineroutes":[{"carrier":"AA","carrier_name":"American Airlines","first_flight":"2020-06-04","last_flight":"2020-09-01","common_duration":"139","route_id":"11536","is_new":"0"}]},{"first_flight":"2019-05-04","common_duration":"115","iata_from":"DCA","iata_to":"HHH","id":59110,"city_name_en":"Hilton Head","is_new":"0","filtered_out":0,"airlineroutes":[{"carrier":"AA","carrier_name":"American Airlines","first_flight":"2020-04-11","last_flight":"2020-10-03","common_duration":"115","route_id":"59110","is_new":"0"}]},{"first_flight":null,"common_duration":"215","iata_from":"DCA","iata_to":"IAH","id":11569,"city_name_en":"Houston","is_new":"0","filtered_out":0,"airlineroutes":[{"carrier":"UA","carrier_name":"United Airlines","first_flight":null,"last_flight":"2022-11-13","common_duration":"215","route_id":"11569","is_new":"0"}]},{"first_flight":null,"common_duration":"218","iata_from":"DCA","iata_to":"HOU","id":11566,"city_name_en":"Houston","is_new":"0","filtered_out":0,"airlineroutes":[{"carrier":"WN","carrier_name":"Southwest Airlines","first_flight":null,"last_flight":"2020-06-06","common_duration":"218","route_id":"11566","is_new":"0"}]},{"first_flight":null,"common_duration":"126","iata_from":"DCA","iata_to":"HSV","id":11568,"city_name_en":"Huntsville","is_new":"0","filtered_out":0,"airlineroutes":[{"carrier":"AA","carrier_name":"American Airlines","first_flight":null,"last_flight":"2022-11-18","common_duration":"126","route_id":"11568","is_new":"0"}]},{"first_flight":null,"common_duration":"114","iata_from":"DCA","iata_to":"IND","id":11571,"city_name_en":"Indianapolis","is_new":"0","filtered_out":0,"airlineroutes":[{"carrier":"AA","carrier_name":"American Airlines","first_flight":null,"last_flight":"2022-11-18","common_duration":"114","route_id":"11571","is_new":"0"}]},{"first_flight":null,"common_duration":"163","iata_from":"DCA","iata_to":"JAN","id":11572,"city_name_en":"Jackson","is_new":"0","filtered_out":0,"airlineroutes":[{"carrier":"AA","carrier_name":"American Airlines","first_flight":null,"last_flight":"2022-11-18","common_duration":"163","route_id":"11572","is_new":"0"}]},{"first_flight":null,"common_duration":"128","iata_from":"DCA","iata_to":"JAX","id":11573,"city_name_en":"Jacksonville","is_new":"0","filtered_out":0,"airlineroutes":[{"carrier":"AA","carrier_name":"American Airlines","first_flight":null,"last_flight":"2022-11-18","common_duration":"128","route_id":"11573","is_new":"0"}]},{"first_flight":null,"common_duration":"170","iata_from":"DCA","iata_to":"MCI","id":11581,"city_name_en":"Kansas City","is_new":"0","filtered_out":0,"airlineroutes":[{"carrier":"AA","carrier_name":"American Airlines","first_flight":null,"last_flight":"2022-11-18","common_duration":"174","route_id":"11581","is_new":"0"},{"carrier":"WN","carrier_name":"Southwest Airlines","first_flight":null,"last_flight":"2020-06-06","common_duration":"170","route_id":"11581","is_new":"0"}]},{"first_flight":"2018-06-16","common_duration":"181","iata_from":"DCA","iata_to":"EYW","id":11561,"city_name_en":"Key West","is_new":"0","filtered_out":0,"airlineroutes":[{"carrier":"AA","carrier_name":"American Airlines","first_flight":null,"last_flight":"2022-11-18","common_duration":"181","route_id":"11561","is_new":"0"}]},{"first_flight":null,"common_duration":"98","iata_from":"DCA","iata_to":"TYS","id":11620,"city_name_en":"Knoxville","is_new":"0","filtered_out":0,"airlineroutes":[{"carrier":"AA","carrier_name":"American Airlines","first_flight":null,"last_flight":"2022-11-12","common_duration":"98","route_id":"11620","is_new":"0"}]},{"first_flight":null,"common_duration":"104","iata_from":"DCA","iata_to":"LAN","id":11575,"city_name_en":"Lansing","is_new":"0","filtered_out":0,"airlineroutes":[{"carrier":"AA","carrier_name":"American Airlines","first_flight":null,"last_flight":"2022-11-18","common_duration":"104","route_id":"11575","is_new":"0"}]},{"first_flight":null,"common_duration":"332","iata_from":"DCA","iata_to":"LAS","id":11576,"city_name_en":"Las Vegas","is_new":"0","filtered_out":0,"airlineroutes":[{"carrier":"AA","carrier_name":"American Airlines","first_flight":null,"last_flight":"2022-11-12","common_duration":"332","route_id":"11576","is_new":"0"}]},{"first_flight":null,"common_duration":"99","iata_from":"DCA","iata_to":"LEX","id":11578,"city_name_en":"Lexington","is_new":"0","filtered_out":0,"airlineroutes":[{"carrier":"DL","carrier_name":"Delta Air Lines","first_flight":null,"last_flight":"2022-03-19","common_duration":"99","route_id":"11578","is_new":"0"}]},{"first_flight":"2018-04-03","common_duration":"172","iata_from":"DCA","iata_to":"LIT","id":11580,"city_name_en":"Little Rock","is_new":"0","filtered_out":0,"airlineroutes":[{"carrier":"AA","carrier_name":"American Airlines","first_flight":null,"last_flight":"2022-11-12","common_duration":"172","route_id":"11580","is_new":"0"}]},{"first_flight":null,"common_duration":"362","iata_from":"DCA","iata_to":"LAX","id":11577,"city_name_en":"Los Angeles","is_new":"0","filtered_out":0,"airlineroutes":[{"carrier":"AA","carrier_name":"American Airlines","first_flight":null,"last_flight":"2022-11-12","common_duration":"369","route_id":"11577","is_new":"0"},{"carrier":"AS","carrier_name":"Alaska Airlines","first_flight":null,"last_flight":"2020-11-30","common_duration":"361","route_id":"11577","is_new":"0"},{"carrier":"DL","carrier_name":"Delta Air Lines","first_flight":null,"last_flight":"2022-11-12","common_duration":"358","route_id":"11577","is_new":"0"}]},{"first_flight":null,"common_duration":"114","iata_from":"DCA","iata_to":"SDF","id":11610,"city_name_en":"Louisville","is_new":"0","filtered_out":0,"airlineroutes":[{"carrier":"AA","carrier_name":"American Airlines","first_flight":null,"last_flight":"2022-11-18","common_duration":"114","route_id":"11610","is_new":"0"}]},{"first_flight":"2019-08-25","common_duration":"145","iata_from":"DCA","iata_to":"MSN","id":11589,"city_name_en":"Madison","is_new":"0","filtered_out":0,"airlineroutes":[{"carrier":"DL","carrier_name":"Delta Air Lines","first_flight":null,"last_flight":"2022-03-19","common_duration":"145","route_id":"11589","is_new":"0"}]},{"first_flight":null,"common_duration":"91","iata_from":"DCA","iata_to":"MHT","id":11586,"city_name_en":"Manchester","is_new":"0","filtered_out":0,"airlineroutes":[{"carrier":"AA","carrier_name":"American Airlines","first_flight":null,"last_flight":"2022-11-18","common_duration":"91","route_id":"11586","is_new":"0"}]},{"first_flight":null,"common_duration":"153","iata_from":"DCA","iata_to":"MEM","id":11584,"city_name_en":"Memphis","is_new":"0","filtered_out":0,"airlineroutes":[{"carrier":"AA","carrier_name":"American Airlines","first_flight":null,"last_flight":"2022-11-18","common_duration":"153","route_id":"11584","is_new":"0"}]},{"first_flight":"2018-03-10","common_duration":"170","iata_from":"DCA","iata_to":"MIA","id":11587,"city_name_en":"Miami","is_new":"0","filtered_out":0,"airlineroutes":[{"carrier":"AA","carrier_name":"American Airlines","first_flight":null,"last_flight":"2022-11-12","common_duration":"170","route_id":"11587","is_new":"0"}]},{"first_flight":null,"common_duration":"125","iata_from":"DCA","iata_to":"MKE","id":11588,"city_name_en":"Milwaukee","is_new":"0","filtered_out":0,"airlineroutes":[{"carrier":"WN","carrier_name":"Southwest Airlines","first_flight":null,"last_flight":"2020-06-06","common_duration":"125","route_id":"11588","is_new":"0"}]},{"first_flight":null,"common_duration":"167","iata_from":"DCA","iata_to":"MSP","id":11590,"city_name_en":"Minneapolis","is_new":"0","filtered_out":0,"airlineroutes":[{"carrier":"AA","carrier_name":"American Airlines","first_flight":null,"last_flight":"2022-11-18","common_duration":"173","route_id":"11590","is_new":"0"},{"carrier":"DL","carrier_name":"Delta Air Lines","first_flight":null,"last_flight":"2022-11-12","common_duration":"166","route_id":"11590","is_new":"0"}]},{"first_flight":"2018-06-07","common_duration":"133","iata_from":"DCA","iata_to":"MGM","id":11585,"city_name_en":"Montgomery","is_new":"0","filtered_out":0,"airlineroutes":[{"carrier":"AA","carrier_name":"American Airlines","first_flight":null,"last_flight":"2022-11-12","common_duration":"133","route_id":"11585","is_new":"0"}]},{"first_flight":null,"common_duration":"98","iata_from":"DCA","iata_to":"YUL","id":11624,"city_name_en":"Montreal","is_new":"0","filtered_out":0,"airlineroutes":[{"carrier":"AC","carrier_name":"Air Canada","first_flight":null,"last_flight":"2022-03-19","common_duration":"98","route_id":"11624","is_new":"0"}]},{"first_flight":null,"common_duration":"88","iata_from":"DCA","iata_to":"MYR","id":11593,"city_name_en":"Myrtle Beach","is_new":"0","filtered_out":0,"airlineroutes":[{"carrier":"AA","carrier_name":"American Airlines","first_flight":null,"last_flight":"2022-11-13","common_duration":"88","route_id":"11593","is_new":"0"}]},{"first_flight":"2018-05-25","common_duration":"85","iata_from":"DCA","iata_to":"ACK","id":11532,"city_name_en":"Nantucket","is_new":"0","filtered_out":0,"airlineroutes":[{"carrier":"AA","carrier_name":"American Airlines","first_flight":"2020-06-19","last_flight":"2020-09-08","common_duration":"96","route_id":"11532","is_new":"0"},{"carrier":"B6","carrier_name":"JetBlue Airways","first_flight":"2020-05-22","last_flight":"2022-03-19","common_duration":"85","route_id":"11532","is_new":"0"}]},{"first_flight":null,"common_duration":"124","iata_from":"DCA","iata_to":"BNA","id":11540,"city_name_en":"Nashville","is_new":"0","filtered_out":0,"airlineroutes":[{"carrier":"AA","carrier_name":"American Airlines","first_flight":null,"last_flight":"2022-11-18","common_duration":"125","route_id":"11540","is_new":"0"},{"carrier":"WN","carrier_name":"Southwest Airlines","first_flight":null,"last_flight":"2020-06-06","common_duration":"120","route_id":"11540","is_new":"0"}]},{"first_flight":"2018-06-16","common_duration":"180","iata_from":"DCA","iata_to":"NAS","id":11594,"city_name_en":"Nassau","is_new":"0","filtered_out":0,"airlineroutes":[{"carrier":"AA","carrier_name":"American Airlines","first_flight":null,"last_flight":"2022-11-18","common_duration":"181","route_id":"11594","is_new":"0"},{"carrier":"B6","carrier_name":"JetBlue Airways","first_flight":null,"last_flight":"2020-04-25","common_duration":"161","route_id":"11594","is_new":"0"}]},{"first_flight":null,"common_duration":"177","iata_from":"DCA","iata_to":"MSY","id":11591,"city_name_en":"New Orleans","is_new":"0","filtered_out":0,"airlineroutes":[{"carrier":"AA","carrier_name":"American Airlines","first_flight":null,"last_flight":"2022-11-12","common_duration":"181","route_id":"11591","is_new":"0"},{"carrier":"WN","carrier_name":"Southwest Airlines","first_flight":null,"last_flight":"2020-06-06","common_duration":"175","route_id":"11591","is_new":"0"}]},{"first_flight":null,"common_duration":"83","iata_from":"DCA","iata_to":"LGA","id":11579,"city_name_en":"New York","is_new":"0","filtered_out":0,"airlineroutes":[{"carrier":"AA","carrier_name":"American Airlines","first_flight":null,"last_flight":"2022-11-18","common_duration":"81","route_id":"11579","is_new":"0"},{"carrier":"DL","carrier_name":"Delta Air Lines","first_flight":null,"last_flight":"2022-11-12","common_duration":"85","route_id":"11579","is_new":"0"}]},{"first_flight":"2019-06-15","common_duration":"85","iata_from":"DCA","iata_to":"JFK","id":11574,"city_name_en":"New York","is_new":"0","filtered_out":0,"airlineroutes":[{"carrier":"AA","carrier_name":"American Airlines","first_flight":null,"last_flight":"2022-11-18","common_duration":"85","route_id":"11574","is_new":"0"},{"carrier":"DL","carrier_name":"Delta Air Lines","first_flight":null,"last_flight":"2022-11-12","common_duration":"82","route_id":"11574","is_new":"0"}]},{"first_flight":null,"common_duration":"82","iata_from":"DCA","iata_to":"EWR","id":11560,"city_name_en":"Newark","is_new":"0","filtered_out":0,"airlineroutes":[{"carrier":"UA","carrier_name":"United Airlines","first_flight":null,"last_flight":"2022-11-12","common_duration":"82","route_id":"11560","is_new":"0"}]},{"first_flight":null,"common_duration":"59","iata_from":"DCA","iata_to":"ORF","id":11597,"city_name_en":"Norfolk","is_new":"0","filtered_out":0,"airlineroutes":[{"carrier":"AA","carrier_name":"American Airlines","first_flight":null,"last_flight":"2022-11-12","common_duration":"59","route_id":"11597","is_new":"0"}]},{"first_flight":"2018-11-04","common_duration":"209","iata_from":"DCA","iata_to":"OKC","id":55425,"city_name_en":"Oklahoma City","is_new":"0","filtered_out":0,"airlineroutes":[{"carrier":"WN","carrier_name":"Southwest Airlines","first_flight":null,"last_flight":"2020-06-06","common_duration":"205","route_id":"55425","is_new":"0"},{"carrier":"AA","carrier_name":"American Airlines","first_flight":null,"last_flight":"2022-11-12","common_duration":"217","route_id":"55425","is_new":"0"}]},{"first_flight":null,"common_duration":"180","iata_from":"DCA","iata_to":"OMA","id":11595,"city_name_en":"Omaha","is_new":"0","filtered_out":0,"airlineroutes":[{"carrier":"DL","carrier_name":"Delta Air Lines","first_flight":null,"last_flight":"2022-03-19","common_duration":"189","route_id":"11595","is_new":"0"},{"carrier":"WN","carrier_name":"Southwest Airlines","first_flight":null,"last_flight":"2020-06-06","common_duration":"180","route_id":"11595","is_new":"0"}]},{"first_flight":"2018-03-10","common_duration":"148","iata_from":"DCA","iata_to":"MCO","id":11582,"city_name_en":"Orlando","is_new":"0","filtered_out":0,"airlineroutes":[{"carrier":"AA","carrier_name":"American Airlines","first_flight":null,"last_flight":"2022-11-12","common_duration":"151","route_id":"11582","is_new":"0"},{"carrier":"B6","carrier_name":"JetBlue Airways","first_flight":null,"last_flight":"2022-03-25","common_duration":"146","route_id":"11582","is_new":"0"},{"carrier":"WN","carrier_name":"Southwest Airlines","first_flight":null,"last_flight":"2020-06-06","common_duration":"145","route_id":"11582","is_new":"0"}]},{"first_flight":null,"common_duration":"92","iata_from":"DCA","iata_to":"YOW","id":11623,"city_name_en":"Ottawa","is_new":"0","filtered_out":0,"airlineroutes":[{"carrier":"AC","carrier_name":"Air Canada","first_flight":null,"last_flight":"2022-03-20","common_duration":"92","route_id":"11623","is_new":"0"}]},{"first_flight":"2020-01-07","common_duration":"153","iata_from":"DCA","iata_to":"ECP","id":63729,"city_name_en":"Panama City","is_new":"0","filtered_out":0,"airlineroutes":[{"carrier":"AA","carrier_name":"American Airlines","first_flight":null,"last_flight":"2022-11-12","common_duration":"153","route_id":"63729","is_new":"0"}]},{"first_flight":null,"common_duration":"149","iata_from":"DCA","iata_to":"PNS","id":11603,"city_name_en":"Pensacola","is_new":"0","filtered_out":0,"airlineroutes":[{"carrier":"AA","carrier_name":"American Airlines","first_flight":null,"last_flight":"2022-11-18","common_duration":"149","route_id":"11603","is_new":"0"}]},{"first_flight":null,"common_duration":"65","iata_from":"DCA","iata_to":"PHL","id":11600,"city_name_en":"Philadelphia","is_new":"0","filtered_out":0,"airlineroutes":[{"carrier":"AA","carrier_name":"American Airlines","first_flight":null,"last_flight":"2022-11-18","common_duration":"65","route_id":"11600","is_new":"0"}]},{"first_flight":null,"common_duration":"316","iata_from":"DCA","iata_to":"PHX","id":11601,"city_name_en":"Phoenix","is_new":"0","filtered_out":0,"airlineroutes":[{"carrier":"AA","carrier_name":"American Airlines","first_flight":null,"last_flight":"2022-11-12","common_duration":"316","route_id":"11601","is_new":"0"}]},{"first_flight":null,"common_duration":"68","iata_from":"DCA","iata_to":"PIT","id":11602,"city_name_en":"Pittsburgh","is_new":"0","filtered_out":0,"airlineroutes":[{"carrier":"AA","carrier_name":"American Airlines","first_flight":null,"last_flight":"2022-11-13","common_duration":"68","route_id":"11602","is_new":"0"}]},{"first_flight":null,"common_duration":"96","iata_from":"DCA","iata_to":"PWM","id":11605,"city_name_en":"Portland","is_new":"0","filtered_out":0,"airlineroutes":[{"carrier":"AA","carrier_name":"American Airlines","first_flight":null,"last_flight":"2022-11-18","common_duration":"96","route_id":"11605","is_new":"0"}]},{"first_flight":null,"common_duration":"359","iata_from":"DCA","iata_to":"PDX","id":11599,"city_name_en":"Portland","is_new":"0","filtered_out":0,"airlineroutes":[{"carrier":"AS","carrier_name":"Alaska Airlines","first_flight":null,"last_flight":"2020-11-30","common_duration":"359","route_id":"11599","is_new":"0"}]},{"first_flight":null,"common_duration":"81","iata_from":"DCA","iata_to":"PVD","id":11604,"city_name_en":"Providence","is_new":"0","filtered_out":0,"airlineroutes":[{"carrier":"AA","carrier_name":"American Airlines","first_flight":null,"last_flight":"2022-11-18","common_duration":"82","route_id":"11604","is_new":"0"},{"carrier":"WN","carrier_name":"Southwest Airlines","first_flight":null,"last_flight":"2020-06-06","common_duration":"80","route_id":"11604","is_new":"0"}]},{"first_flight":null,"common_duration":"82","iata_from":"DCA","iata_to":"ROC","id":11607,"city_name_en":"Rochester","is_new":"0","filtered_out":0,"airlineroutes":[{"carrier":"AA","carrier_name":"American Airlines","first_flight":null,"last_flight":"2022-11-18","common_duration":"82","route_id":"11607","is_new":"0"}]},{"first_flight":null,"common_duration":"145","iata_from":"DCA","iata_to":"STL","id":11616,"city_name_en":"Saint Louis","is_new":"0","filtered_out":0,"airlineroutes":[{"carrier":"AA","carrier_name":"American Airlines","first_flight":null,"last_flight":"2022-11-13","common_duration":"149","route_id":"11616","is_new":"0"},{"carrier":"WN","carrier_name":"Southwest Airlines","first_flight":null,"last_flight":"2020-06-06","common_duration":"140","route_id":"11616","is_new":"0"}]},{"first_flight":null,"common_duration":"296","iata_from":"DCA","iata_to":"SLC","id":11614,"city_name_en":"Salt Lake City","is_new":"0","filtered_out":0,"airlineroutes":[{"carrier":"DL","carrier_name":"Delta Air Lines","first_flight":null,"last_flight":"2022-03-19","common_duration":"296","route_id":"11614","is_new":"0"}]},{"first_flight":"2018-04-25","common_duration":"374","iata_from":"DCA","iata_to":"SFO","id":11612,"city_name_en":"San Francisco","is_new":"0","filtered_out":0,"airlineroutes":[{"carrier":"AS","carrier_name":"Alaska Airlines","first_flight":null,"last_flight":"2020-11-30","common_duration":"374","route_id":"11612","is_new":"0"},{"carrier":"UA","carrier_name":"United Airlines","first_flight":null,"last_flight":"2022-11-12","common_duration":"376","route_id":"11612","is_new":"0"}]},{"first_flight":null,"common_duration":"227","iata_from":"DCA","iata_to":"SJU","id":11613,"city_name_en":"San Juan","is_new":"0","filtered_out":0,"airlineroutes":[{"carrier":"B6","carrier_name":"JetBlue Airways","first_flight":null,"last_flight":"2022-03-19","common_duration":"227","route_id":"11613","is_new":"0"}]},{"first_flight":null,"common_duration":"161","iata_from":"DCA","iata_to":"SRQ","id":11615,"city_name_en":"Sarasota","is_new":"0","filtered_out":0,"airlineroutes":[{"carrier":"AA","carrier_name":"American Airlines","first_flight":null,"last_flight":"2022-11-12","common_duration":"161","route_id":"11615","is_new":"0"}]},{"first_flight":null,"common_duration":"116","iata_from":"DCA","iata_to":"SAV","id":11609,"city_name_en":"Savannah","is_new":"0","filtered_out":0,"airlineroutes":[{"carrier":"AA","carrier_name":"American Airlines","first_flight":null,"last_flight":"2022-11-18","common_duration":"116","route_id":"11609","is_new":"0"}]},{"first_flight":null,"common_duration":"366","iata_from":"DCA","iata_to":"SEA","id":11611,"city_name_en":"Seattle","is_new":"0","filtered_out":0,"airlineroutes":[{"carrier":"AS","carrier_name":"Alaska Airlines","first_flight":null,"last_flight":"2020-11-30","common_duration":"366","route_id":"11611","is_new":"0"}]},{"first_flight":null,"common_duration":"79","iata_from":"DCA","iata_to":"SYR","id":11617,"city_name_en":"Syracuse","is_new":"0","filtered_out":0,"airlineroutes":[{"carrier":"AA","carrier_name":"American Airlines","first_flight":null,"last_flight":"2022-11-18","common_duration":"79","route_id":"11617","is_new":"0"}]},{"first_flight":"2018-02-15","common_duration":"133","iata_from":"DCA","iata_to":"TLH","id":11618,"city_name_en":"Tallahassee","is_new":"0","filtered_out":0,"airlineroutes":[{"carrier":"AA","carrier_name":"American Airlines","first_flight":null,"last_flight":"2022-11-18","common_duration":"133","route_id":"11618","is_new":"0"}]},{"first_flight":null,"common_duration":"150","iata_from":"DCA","iata_to":"TPA","id":11619,"city_name_en":"Tampa","is_new":"0","filtered_out":0,"airlineroutes":[{"carrier":"AA","carrier_name":"American Airlines","first_flight":null,"last_flight":"2022-11-18","common_duration":"152","route_id":"11619","is_new":"0"},{"carrier":"WN","carrier_name":"Southwest Airlines","first_flight":null,"last_flight":"2020-06-06","common_duration":"150","route_id":"11619","is_new":"0"}]},{"first_flight":null,"common_duration":"96","iata_from":"DCA","iata_to":"YYZ","id":11625,"city_name_en":"Toronto","is_new":"0","filtered_out":0,"airlineroutes":[{"carrier":"AA","carrier_name":"American Airlines","first_flight":null,"last_flight":"2022-11-18","common_duration":"102","route_id":"11625","is_new":"0"},{"carrier":"AC","carrier_name":"Air Canada","first_flight":null,"last_flight":"2022-03-19","common_duration":"91","route_id":"11625","is_new":"0"}]},{"first_flight":"2020-06-20","common_duration":"135","iata_from":"DCA","iata_to":"TVC","id":66746,"city_name_en":"Traverse City","is_new":"1","filtered_out":0,"airlineroutes":[{"carrier":"AA","carrier_name":"American Airlines","first_flight":"2020-06-20","last_flight":"2020-09-05","common_duration":"135","route_id":"66746","is_new":"1"}]},{"first_flight":null,"common_duration":"166","iata_from":"DCA","iata_to":"VPS","id":11621,"city_name_en":"Valparaiso","is_new":"0","filtered_out":0,"airlineroutes":[{"carrier":"AA","carrier_name":"American Airlines","first_flight":null,"last_flight":"2022-11-12","common_duration":"166","route_id":"11621","is_new":"0"}]},{"first_flight":"2018-06-22","common_duration":"90","iata_from":"DCA","iata_to":"MVY","id":11592,"city_name_en":"Vineyard Haven","is_new":"0","filtered_out":0,"airlineroutes":[{"carrier":"AA","carrier_name":"American Airlines","first_flight":"2020-06-19","last_flight":"2020-09-08","common_duration":"90","route_id":"11592","is_new":"0"},{"carrier":"B6","carrier_name":"JetBlue Airways","first_flight":"2020-06-12","last_flight":"2022-03-19","common_duration":"90","route_id":"11592","is_new":"1"}]},{"first_flight":null,"common_duration":"157","iata_from":"DCA","iata_to":"PBI","id":11598,"city_name_en":"West Palm Beach","is_new":"0","filtered_out":0,"airlineroutes":[{"carrier":"AA","carrier_name":"American Airlines","first_flight":null,"last_flight":"2022-11-18","common_duration":"159","route_id":"11598","is_new":"0"},{"carrier":"B6","carrier_name":"JetBlue Airways","first_flight":null,"last_flight":"2022-03-25","common_duration":"150","route_id":"11598","is_new":"0"}]},{"first_flight":null,"common_duration":"76","iata_from":"DCA","iata_to":"HPN","id":11567,"city_name_en":"White Plains","is_new":"0","filtered_out":0,"airlineroutes":[{"carrier":"AA","carrier_name":"American Airlines","first_flight":null,"last_flight":"2022-11-12","common_duration":"76","route_id":"11567","is_new":"0"}]},{"first_flight":"2018-04-07","common_duration":"86","iata_from":"DCA","iata_to":"ILM","id":11570,"city_name_en":"Wilmington","is_new":"0","filtered_out":0,"airlineroutes":[{"carrier":"AA","carrier_name":"American Airlines","first_flight":null,"last_flight":"2022-11-12","common_duration":"86","route_id":"11570","is_new":"0"}]},{"first_flight":null,"common_duration":"79","iata_from":"DCA","iata_to":"BDL","id":11537,"city_name_en":"Windsor Locks","is_new":"0","filtered_out":0,"airlineroutes":[{"carrier":"AA","carrier_name":"American Airlines","first_flight":null,"last_flight":"2022-11-18","common_duration":"79","route_id":"11537","is_new":"0"}]}]}]