[{"iata_from":"EXT","routes":[{"first_flight":"2019-10-29","common_duration":"145","iata_from":"EXT","iata_to":"ALC","id":15062,"city_name_en":"Alicante","is_new":"0","filtered_out":0,"airlineroutes":[{"carrier":"FR","carrier_name":"Ryanair","first_flight":null,"last_flight":"2021-11-05","common_duration":"145","route_id":"15062","is_new":"0"}]},{"first_flight":null,"common_duration":"95","iata_from":"EXT","iata_to":"AMS","id":15063,"city_name_en":"Amsterdam","is_new":"0","filtered_out":0,"airlineroutes":[{"carrier":"BE","carrier_name":"Flybe","first_flight":null,"last_flight":"2022-04-08","common_duration":"95","route_id":"15063","is_new":"0"}]},{"first_flight":null,"common_duration":"80","iata_from":"EXT","iata_to":"BHD","id":15064,"city_name_en":"Belfast","is_new":"0","filtered_out":0,"airlineroutes":[{"carrier":"BE","carrier_name":"Flybe","first_flight":null,"last_flight":"2022-04-08","common_duration":"80","route_id":"15064","is_new":"0"}]},{"first_flight":"2018-04-28","common_duration":"95","iata_from":"EXT","iata_to":"EGC","id":15069,"city_name_en":"Bergerac","is_new":"0","filtered_out":0,"airlineroutes":[{"carrier":"BE","carrier_name":"Flybe","first_flight":"2020-05-30","last_flight":"2020-09-12","common_duration":"95","route_id":"15069","is_new":"0"}]},{"first_flight":"2018-03-17","common_duration":"130","iata_from":"EXT","iata_to":"CMF","id":15066,"city_name_en":"Chambery","is_new":"0","filtered_out":0,"airlineroutes":[{"carrier":"BE","carrier_name":"Flybe","first_flight":null,"last_flight":"2020-04-11","common_duration":"130","route_id":"15066","is_new":"0"}]},{"first_flight":null,"common_duration":"75","iata_from":"EXT","iata_to":"DUB","id":15067,"city_name_en":"Dublin","is_new":"0","filtered_out":0,"airlineroutes":[{"carrier":"BE","carrier_name":"Flybe","first_flight":null,"last_flight":"2022-04-08","common_duration":"75","route_id":"15067","is_new":"0"}]},{"first_flight":null,"common_duration":"90","iata_from":"EXT","iata_to":"EDI","id":15068,"city_name_en":"Edinburgh","is_new":"0","filtered_out":0,"airlineroutes":[{"carrier":"BE","carrier_name":"Flybe","first_flight":null,"last_flight":"2022-04-03","common_duration":"90","route_id":"15068","is_new":"0"}]},{"first_flight":"2018-03-17","common_duration":"125","iata_from":"EXT","iata_to":"GVA","id":15073,"city_name_en":"Geneva","is_new":"0","filtered_out":0,"airlineroutes":[{"carrier":"BE","carrier_name":"Flybe","first_flight":null,"last_flight":"2020-04-11","common_duration":"125","route_id":"15073","is_new":"0"}]},{"first_flight":null,"common_duration":"90","iata_from":"EXT","iata_to":"GLA","id":15072,"city_name_en":"Glasgow","is_new":"0","filtered_out":0,"airlineroutes":[{"carrier":"BE","carrier_name":"Flybe","first_flight":null,"last_flight":"2022-04-03","common_duration":"90","route_id":"15072","is_new":"0"}]},{"first_flight":"2019-04-06","common_duration":"45","iata_from":"EXT","iata_to":"GCI","id":15071,"city_name_en":"Guernsey","is_new":"0","filtered_out":0,"airlineroutes":[{"carrier":"BE","carrier_name":"Flybe","first_flight":null,"last_flight":"2022-04-03","common_duration":"45","route_id":"15071","is_new":"0"}]},{"first_flight":null,"common_duration":"70","iata_from":"EXT","iata_to":"LCY","id":15075,"city_name_en":"London","is_new":"0","filtered_out":0,"airlineroutes":[{"carrier":"BE","carrier_name":"Flybe","first_flight":null,"last_flight":"2022-04-03","common_duration":"70","route_id":"15075","is_new":"0"}]},{"first_flight":"2019-04-03","common_duration":"155","iata_from":"EXT","iata_to":"AGP","id":15061,"city_name_en":"Malaga","is_new":"0","filtered_out":0,"airlineroutes":[{"carrier":"FR","carrier_name":"Ryanair","first_flight":null,"last_flight":"2021-11-02","common_duration":"155","route_id":"15061","is_new":"0"}]},{"first_flight":null,"common_duration":"70","iata_from":"EXT","iata_to":"MAN","id":15076,"city_name_en":"Manchester","is_new":"0","filtered_out":0,"airlineroutes":[{"carrier":"BE","carrier_name":"Flybe","first_flight":null,"last_flight":"2022-04-08","common_duration":"70","route_id":"15076","is_new":"0"}]},{"first_flight":null,"common_duration":"75","iata_from":"EXT","iata_to":"NCL","id":15077,"city_name_en":"Newcastle","is_new":"0","filtered_out":0,"airlineroutes":[{"carrier":"BE","carrier_name":"Flybe","first_flight":null,"last_flight":"2022-04-08","common_duration":"75","route_id":"15077","is_new":"0"}]},{"first_flight":null,"common_duration":"90","iata_from":"EXT","iata_to":"CDG","id":15065,"city_name_en":"Paris","is_new":"0","filtered_out":0,"airlineroutes":[{"carrier":"BE","carrier_name":"Flybe","first_flight":null,"last_flight":"2022-04-03","common_duration":"90","route_id":"15065","is_new":"0"}]},{"first_flight":"2019-04-06","common_duration":"45","iata_from":"EXT","iata_to":"JER","id":15074,"city_name_en":"Saint Peter","is_new":"0","filtered_out":0,"airlineroutes":[{"carrier":"BE","carrier_name":"Flybe","first_flight":null,"last_flight":"2022-04-02","common_duration":"45","route_id":"15074","is_new":"0"}]},{"first_flight":"2019-04-02","common_duration":"200","iata_from":"EXT","iata_to":"MLA","id":59304,"city_name_en":"Valletta","is_new":"0","filtered_out":0,"airlineroutes":[{"carrier":"FR","carrier_name":"Ryanair","first_flight":null,"last_flight":"2021-11-05","common_duration":"200","route_id":"59304","is_new":"0"}]}]}]