[{"iata_from":"GUA","routes":[{"first_flight":null,"common_duration":"208","iata_from":"GUA","iata_to":"ATL","id":17755,"city_name_en":"Atlanta","is_new":"0","filtered_out":0,"airlineroutes":[{"carrier":"DL","carrier_name":"Delta Air Lines","first_flight":null,"last_flight":"2022-11-12","common_duration":"208","route_id":"17755","is_new":"0"}]},{"first_flight":null,"common_duration":"80","iata_from":"GUA","iata_to":"BZE","id":17757,"city_name_en":"Belize City","is_new":"0","filtered_out":0,"airlineroutes":[{"carrier":"5U","carrier_name":"TAG","first_flight":null,"last_flight":"2020-12-31","common_duration":"80","route_id":"17757","is_new":"0"}]},{"first_flight":null,"common_duration":"195","iata_from":"GUA","iata_to":"BOG","id":17756,"city_name_en":"Bogota","is_new":"0","filtered_out":0,"airlineroutes":[{"carrier":"AV","carrier_name":"AVIANCA","first_flight":null,"last_flight":"2021-03-27","common_duration":"195","route_id":"17756","is_new":"0"}]},{"first_flight":null,"common_duration":"110","iata_from":"GUA","iata_to":"CUN","id":17758,"city_name_en":"Cancun","is_new":"0","filtered_out":0,"airlineroutes":[{"carrier":"Y4","carrier_name":"Volaris","first_flight":null,"last_flight":"2021-09-20","common_duration":"110","route_id":"17758","is_new":"0"}]},{"first_flight":"2018-06-16","common_duration":"312","iata_from":"GUA","iata_to":"ORD","id":17770,"city_name_en":"Chicago","is_new":"0","filtered_out":0,"airlineroutes":[{"carrier":"AA","carrier_name":"American Airlines","first_flight":null,"last_flight":"2022-11-18","common_duration":"312","route_id":"17770","is_new":"0"}]},{"first_flight":null,"common_duration":"217","iata_from":"GUA","iata_to":"DFW","id":17759,"city_name_en":"Dallas","is_new":"0","filtered_out":0,"airlineroutes":[{"carrier":"AA","carrier_name":"American Airlines","first_flight":null,"last_flight":"2022-11-12","common_duration":"217","route_id":"17759","is_new":"0"}]},{"first_flight":null,"common_duration":"60","iata_from":"GUA","iata_to":"FRS","id":17762,"city_name_en":"Flores","is_new":"0","filtered_out":0,"airlineroutes":[{"carrier":"5U","carrier_name":"TAG","first_flight":null,"last_flight":"2020-12-31","common_duration":"60","route_id":"17762","is_new":"0"},{"carrier":"AV","carrier_name":"AVIANCA","first_flight":null,"last_flight":"2021-03-27","common_duration":"65","route_id":"17762","is_new":"0"}]},{"first_flight":null,"common_duration":"163","iata_from":"GUA","iata_to":"FLL","id":17761,"city_name_en":"Fort Lauderdale","is_new":"0","filtered_out":0,"airlineroutes":[{"carrier":"NK","carrier_name":"Spirit Airlines","first_flight":null,"last_flight":"2020-06-09","common_duration":"163","route_id":"17761","is_new":"0"}]},{"first_flight":null,"common_duration":"181","iata_from":"GUA","iata_to":"IAH","id":17765,"city_name_en":"Houston","is_new":"0","filtered_out":0,"airlineroutes":[{"carrier":"UA","carrier_name":"United Airlines","first_flight":null,"last_flight":"2022-11-13","common_duration":"181","route_id":"17765","is_new":"0"},{"carrier":"NK","carrier_name":"Spirit Airlines","first_flight":null,"last_flight":"2020-06-08","common_duration":"188","route_id":"17765","is_new":"0"}]},{"first_flight":null,"common_duration":"319","iata_from":"GUA","iata_to":"LAX","id":17766,"city_name_en":"Los Angeles","is_new":"0","filtered_out":0,"airlineroutes":[{"carrier":"AV","carrier_name":"AVIANCA","first_flight":null,"last_flight":"2021-03-27","common_duration":"319","route_id":"17766","is_new":"0"},{"carrier":"DL","carrier_name":"Delta Air Lines","first_flight":null,"last_flight":"2022-03-19","common_duration":"318","route_id":"17766","is_new":"0"},{"carrier":"Q6","carrier_name":"Volaris Costa Rica","first_flight":null,"last_flight":"2021-11-07","common_duration":"349","route_id":"17766","is_new":"0"}]},{"first_flight":"2018-10-01","common_duration":"109","iata_from":"GUA","iata_to":"MGA","id":17768,"city_name_en":"Managua","is_new":"0","filtered_out":0,"airlineroutes":[{"carrier":"CM","carrier_name":"Copa Airlines","first_flight":null,"last_flight":"2022-01-06","common_duration":"82","route_id":"17768","is_new":"0"},{"carrier":"TA","carrier_name":"TACA","first_flight":null,"last_flight":"2021-03-27","common_duration":"109","route_id":"17768","is_new":"0"}]},{"first_flight":"2018-05-05","common_duration":"145","iata_from":"GUA","iata_to":"MEX","id":17767,"city_name_en":"Mexico City","is_new":"0","filtered_out":0,"airlineroutes":[{"carrier":"4O","carrier_name":"Interjet","first_flight":null,"last_flight":"2022-04-14","common_duration":"145","route_id":"17767","is_new":"0"},{"carrier":"AM","carrier_name":"Aeromexico","first_flight":null,"last_flight":"2021-03-27","common_duration":"140","route_id":"17767","is_new":"0"},{"carrier":"Q6","carrier_name":"Volaris Costa Rica","first_flight":null,"last_flight":"2022-04-09","common_duration":"144","route_id":"17767","is_new":"0"}]},{"first_flight":null,"common_duration":"165","iata_from":"GUA","iata_to":"MIA","id":17769,"city_name_en":"Miami","is_new":"0","filtered_out":0,"airlineroutes":[{"carrier":"AA","carrier_name":"American Airlines","first_flight":null,"last_flight":"2022-11-12","common_duration":"165","route_id":"17769","is_new":"0"}]},{"first_flight":"2019-03-16","common_duration":"275","iata_from":"GUA","iata_to":"EWR","id":17760,"city_name_en":"Newark","is_new":"0","filtered_out":0,"airlineroutes":[{"carrier":"UA","carrier_name":"United Airlines","first_flight":null,"last_flight":"2022-11-18","common_duration":"275","route_id":"17760","is_new":"0"}]},{"first_flight":"2018-08-02","common_duration":"184","iata_from":"GUA","iata_to":"MCO","id":55667,"city_name_en":"Orlando","is_new":"0","filtered_out":0,"airlineroutes":[{"carrier":"NK","carrier_name":"Spirit Airlines","first_flight":null,"last_flight":"2020-06-08","common_duration":"184","route_id":"55667","is_new":"0"}]},{"first_flight":null,"common_duration":"146","iata_from":"GUA","iata_to":"PTY","id":17772,"city_name_en":"Panama City","is_new":"0","filtered_out":0,"airlineroutes":[{"carrier":"CM","carrier_name":"Copa Airlines","first_flight":null,"last_flight":"2022-01-11","common_duration":"146","route_id":"17772","is_new":"0"}]},{"first_flight":null,"common_duration":"45","iata_from":"GUA","iata_to":"PBR","id":17771,"city_name_en":"Puerto Barrios","is_new":"0","filtered_out":0,"airlineroutes":[{"carrier":"5U","carrier_name":"TAG","first_flight":null,"last_flight":"2020-12-31","common_duration":"45","route_id":"17771","is_new":"0"}]},{"first_flight":"2019-06-16","common_duration":"68","iata_from":"GUA","iata_to":"RTB","id":17773,"city_name_en":"Roatan","is_new":"0","filtered_out":0,"airlineroutes":[{"carrier":"5U","carrier_name":"TAG","first_flight":null,"last_flight":"2020-04-05","common_duration":"68","route_id":"17773","is_new":"0"}]},{"first_flight":null,"common_duration":"100","iata_from":"GUA","iata_to":"SJO","id":17776,"city_name_en":"San Jose","is_new":"0","filtered_out":0,"airlineroutes":[{"carrier":"AV","carrier_name":"AVIANCA","first_flight":null,"last_flight":"2021-03-27","common_duration":"91","route_id":"17776","is_new":"0"},{"carrier":"CM","carrier_name":"Copa Airlines","first_flight":null,"last_flight":"2022-01-11","common_duration":"100","route_id":"17776","is_new":"0"},{"carrier":"Q6","carrier_name":"Volaris Costa Rica","first_flight":null,"last_flight":"2022-04-12","common_duration":"96","route_id":"17776","is_new":"0"}]},{"first_flight":null,"common_duration":"60","iata_from":"GUA","iata_to":"SAP","id":17775,"city_name_en":"San Pedro Sula","is_new":"0","filtered_out":0,"airlineroutes":[{"carrier":"5U","carrier_name":"TAG","first_flight":null,"last_flight":"2020-12-31","common_duration":"60","route_id":"17775","is_new":"0"},{"carrier":"CC","carrier_name":"CM Airlines","first_flight":null,"last_flight":"2020-12-17","common_duration":"60","route_id":"17775","is_new":"0"}]},{"first_flight":null,"common_duration":"48","iata_from":"GUA","iata_to":"SAL","id":17774,"city_name_en":"San Salvador","is_new":"0","filtered_out":0,"airlineroutes":[{"carrier":"AV","carrier_name":"AVIANCA","first_flight":null,"last_flight":"2021-03-27","common_duration":"48","route_id":"17774","is_new":"0"},{"carrier":"IB","carrier_name":"Iberia","first_flight":null,"last_flight":"2022-11-05","common_duration":"55","route_id":"17774","is_new":"0"},{"carrier":"Q6","carrier_name":"Volaris Costa Rica","first_flight":null,"last_flight":"2021-11-07","common_duration":"56","route_id":"17774","is_new":"0"},{"carrier":"5U","carrier_name":"TAG","first_flight":null,"last_flight":"2020-12-25","common_duration":"35","route_id":"17774","is_new":"0"}]},{"first_flight":null,"common_duration":"75","iata_from":"GUA","iata_to":"TGU","id":17777,"city_name_en":"Tegucigalpa","is_new":"0","filtered_out":0,"airlineroutes":[{"carrier":"AV","carrier_name":"AVIANCA","first_flight":null,"last_flight":"2021-03-27","common_duration":"81","route_id":"17777","is_new":"0"},{"carrier":"5U","carrier_name":"TAG","first_flight":null,"last_flight":"2020-12-18","common_duration":"75","route_id":"17777","is_new":"0"},{"carrier":"CC","carrier_name":"CM Airlines","first_flight":null,"last_flight":"2019-12-30","common_duration":"75","route_id":"17777","is_new":"0"}]},{"first_flight":"2018-06-16","common_duration":"248","iata_from":"GUA","iata_to":"IAD","id":17764,"city_name_en":"Washington","is_new":"0","filtered_out":0,"airlineroutes":[{"carrier":"UA","carrier_name":"United Airlines","first_flight":null,"last_flight":"2022-11-11","common_duration":"248","route_id":"17764","is_new":"0"}]}]}]