[{"iata_from":"IGA","routes":[{"first_flight":"2020-02-17","common_duration":"60","iata_from":"IGA","iata_to":"GGT","id":67074,"city_name_en":"George Town","is_new":"1","filtered_out":0,"airlineroutes":[{"carrier":"UP","carrier_name":"Bahamasair","first_flight":null,"last_flight":"2020-02-17","common_duration":"60","route_id":"67074","is_new":"1"}]},{"first_flight":null,"common_duration":"30","iata_from":"IGA","iata_to":"MYG","id":20996,"city_name_en":"Mayaguana","is_new":"0","filtered_out":0,"airlineroutes":[{"carrier":"UP","carrier_name":"Bahamasair","first_flight":null,"last_flight":"2022-11-13","common_duration":"30","route_id":"20996","is_new":"0"}]},{"first_flight":null,"common_duration":"90","iata_from":"IGA","iata_to":"NAS","id":20997,"city_name_en":"Nassau","is_new":"0","filtered_out":0,"airlineroutes":[{"carrier":"UP","carrier_name":"Bahamasair","first_flight":null,"last_flight":"2022-11-17","common_duration":"90","route_id":"20997","is_new":"0"}]}]}]