[{"iata_from":"KBC","routes":[{"first_flight":"2018-03-15","common_duration":"45","iata_from":"KBC","iata_to":"FAI","id":53072,"city_name_en":"Fairbanks","is_new":"0","filtered_out":0,"airlineroutes":[{"carrier":"8V","carrier_name":"Astral Aviation","first_flight":null,"last_flight":"2021-11-07","common_duration":"45","route_id":"53072","is_new":"0"}]},{"first_flight":"2018-03-15","common_duration":"15","iata_from":"KBC","iata_to":"FYU","id":53073,"city_name_en":"Fort Yukon","is_new":"0","filtered_out":0,"airlineroutes":[{"carrier":"8V","carrier_name":"Astral Aviation","first_flight":null,"last_flight":"2021-11-07","common_duration":"15","route_id":"53073","is_new":"0"}]}]}]