[{"iata_from":"LRH","routes":[{"first_flight":"2018-05-26","common_duration":"105","iata_from":"LRH","iata_to":"BHX","id":27664,"city_name_en":"Birmingham","is_new":"0","filtered_out":0,"airlineroutes":[{"carrier":"BE","carrier_name":"Flybe","first_flight":"2020-07-04","last_flight":"2020-08-29","common_duration":"105","route_id":"27664","is_new":"0"}]},{"first_flight":"2018-06-26","common_duration":"75","iata_from":"LRH","iata_to":"BRS","id":27665,"city_name_en":"Bristol","is_new":"0","filtered_out":0,"airlineroutes":[{"carrier":"U2","carrier_name":"easyJet","first_flight":"2020-06-23","last_flight":"2020-08-29","common_duration":"75","route_id":"27665","is_new":"0"}]},{"first_flight":"2018-06-26","common_duration":"75","iata_from":"LRH","iata_to":"GVA","id":27668,"city_name_en":"Geneva","is_new":"0","filtered_out":0,"airlineroutes":[{"carrier":"U2","carrier_name":"easyJet","first_flight":"2020-06-23","last_flight":"2020-08-29","common_duration":"75","route_id":"27668","is_new":"0"}]},{"first_flight":"2018-05-26","common_duration":"105","iata_from":"LRH","iata_to":"LBA","id":27669,"city_name_en":"Leeds","is_new":"0","filtered_out":0,"airlineroutes":[{"carrier":"LS","carrier_name":"Jet2","first_flight":"2020-05-23","last_flight":"2020-09-19","common_duration":"105","route_id":"27669","is_new":"0"}]},{"first_flight":"2020-05-23","common_duration":"90","iata_from":"LRH","iata_to":"STN","id":27675,"city_name_en":"London","is_new":"0","filtered_out":0,"airlineroutes":[{"carrier":"FR","carrier_name":"Ryanair","first_flight":null,"last_flight":"2021-11-04","common_duration":"90","route_id":"27675","is_new":"0"},{"carrier":"LS","carrier_name":"Jet2","first_flight":"2020-05-23","last_flight":"2020-09-19","common_duration":"95","route_id":"27675","is_new":"0"}]},{"first_flight":"2018-05-17","common_duration":"85","iata_from":"LRH","iata_to":"LGW","id":27670,"city_name_en":"London","is_new":"0","filtered_out":0,"airlineroutes":[{"carrier":"U2","carrier_name":"easyJet","first_flight":"2020-06-13","last_flight":"2020-09-19","common_duration":"85","route_id":"27670","is_new":"0"}]},{"first_flight":"2018-05-26","common_duration":"105","iata_from":"LRH","iata_to":"MAN","id":27671,"city_name_en":"Manchester","is_new":"0","filtered_out":0,"airlineroutes":[{"carrier":"LS","carrier_name":"Jet2","first_flight":"2020-05-23","last_flight":"2020-09-19","common_duration":"105","route_id":"27671","is_new":"0"}]},{"first_flight":"2018-09-15","common_duration":"85","iata_from":"LRH","iata_to":"ORY","id":53386,"city_name_en":"Paris","is_new":"0","filtered_out":0,"airlineroutes":[{"carrier":"AF","carrier_name":"Air France","first_flight":null,"last_flight":"2020-10-24","common_duration":"85","route_id":"53386","is_new":"0"}]},{"first_flight":"2019-09-01","common_duration":"35","iata_from":"LRH","iata_to":"PIS","id":27673,"city_name_en":"Poitiers","is_new":"0","filtered_out":0,"airlineroutes":[{"carrier":"CE","carrier_name":"Chalair","first_flight":null,"last_flight":"2021-10-31","common_duration":"35","route_id":"27673","is_new":"1"}]},{"first_flight":"2017-12-21","common_duration":"80","iata_from":"LRH","iata_to":"SOU","id":27674,"city_name_en":"Southampton","is_new":"0","filtered_out":0,"airlineroutes":[{"carrier":"BE","carrier_name":"Flybe","first_flight":"2020-06-03","last_flight":"2020-09-12","common_duration":"80","route_id":"27674","is_new":"0"}]}]}]