[{"iata_from":"PPQ","routes":[{"first_flight":null,"common_duration":"80","iata_from":"PPQ","iata_to":"AKL","id":37005,"city_name_en":"Auckland","is_new":"0","filtered_out":0,"airlineroutes":[{"carrier":"3C","carrier_name":"Air Chathams","first_flight":null,"last_flight":"2020-12-24","common_duration":"80","route_id":"37005","is_new":"0"}]},{"first_flight":null,"common_duration":"45","iata_from":"PPQ","iata_to":"NSN","id":37007,"city_name_en":"Nelson","is_new":"0","filtered_out":0,"airlineroutes":[{"carrier":"S8","carrier_name":"Sounds Air","first_flight":null,"last_flight":"2021-10-07","common_duration":"45","route_id":"37007","is_new":"0"}]},{"first_flight":null,"common_duration":"35","iata_from":"PPQ","iata_to":"BHE","id":37006,"city_name_en":"Woodbourne","is_new":"0","filtered_out":0,"airlineroutes":[{"carrier":"S8","carrier_name":"Sounds Air","first_flight":null,"last_flight":"2021-10-07","common_duration":"35","route_id":"37006","is_new":"0"}]}]}]