[{"iata_from":"SOJ","routes":[{"first_flight":null,"common_duration":"30","iata_from":"SOJ","iata_to":"HFT","id":41837,"city_name_en":"Hammerfest","is_new":"0","filtered_out":0,"airlineroutes":[{"carrier":"WF","carrier_name":"Wideroe","first_flight":null,"last_flight":"2021-03-26","common_duration":"30","route_id":"41837","is_new":"0"}]},{"first_flight":null,"common_duration":"25","iata_from":"SOJ","iata_to":"TOS","id":41838,"city_name_en":"Tromso","is_new":"0","filtered_out":0,"airlineroutes":[{"carrier":"WF","carrier_name":"Wideroe","first_flight":null,"last_flight":"2021-03-26","common_duration":"25","route_id":"41838","is_new":"0"}]}]}]