[{"iata_from":"TBS","routes":[{"first_flight":null,"common_duration":"60","iata_from":"TBS","iata_to":"SCO","id":44065,"city_name_en":"Aktau","is_new":"0","filtered_out":0,"airlineroutes":[{"carrier":"DV","carrier_name":"SCAT Airlines","first_flight":null,"last_flight":"2020-12-17","common_duration":"60","route_id":"44065","is_new":"0"}]},{"first_flight":null,"common_duration":"220","iata_from":"TBS","iata_to":"ALA","id":44030,"city_name_en":"Alma-Ata","is_new":"0","filtered_out":0,"airlineroutes":[{"carrier":"KC","carrier_name":"Air Astana","first_flight":null,"last_flight":"2021-03-26","common_duration":"220","route_id":"44030","is_new":"0"}]},{"first_flight":null,"common_duration":"310","iata_from":"TBS","iata_to":"AMS","id":44031,"city_name_en":"Amsterdam","is_new":"0","filtered_out":0,"airlineroutes":[{"carrier":"A9","carrier_name":"Georgian Airways","first_flight":null,"last_flight":"2022-04-03","common_duration":"310","route_id":"44031","is_new":"0"}]},{"first_flight":null,"common_duration":"120","iata_from":"TBS","iata_to":"ESB","id":63019,"city_name_en":"Ankara","is_new":"0","filtered_out":0,"airlineroutes":[{"carrier":"TK","carrier_name":"Turkish Airlines","first_flight":null,"last_flight":"2021-03-25","common_duration":"120","route_id":"63019","is_new":"0"}]},{"first_flight":null,"common_duration":"178","iata_from":"TBS","iata_to":"ATH","id":44032,"city_name_en":"Athens","is_new":"0","filtered_out":0,"airlineroutes":[{"carrier":"A3","carrier_name":"Aegean Airlines","first_flight":null,"last_flight":"2022-04-03","common_duration":"178","route_id":"44032","is_new":"0"}]},{"first_flight":"2018-09-15","common_duration":"70","iata_from":"TBS","iata_to":"GYD","id":44045,"city_name_en":"Baku","is_new":"0","filtered_out":0,"airlineroutes":[{"carrier":"J2","carrier_name":"AZAL Azerbaijan Airlines","first_flight":null,"last_flight":"2021-04-04","common_duration":"70","route_id":"44045","is_new":"0"},{"carrier":"XY","carrier_name":"Flynas","first_flight":null,"last_flight":"2020-03-27","common_duration":"80","route_id":"44045","is_new":"0"}]},{"first_flight":"2019-11-06","common_duration":"250","iata_from":"TBS","iata_to":"BGY","id":66127,"city_name_en":"Bergamo","is_new":"0","filtered_out":0,"airlineroutes":[{"carrier":"FR","carrier_name":"Ryanair","first_flight":null,"last_flight":"2021-11-04","common_duration":"250","route_id":"66127","is_new":"0"}]},{"first_flight":"2018-03-26","common_duration":"240","iata_from":"TBS","iata_to":"SXF","id":44071,"city_name_en":"Berlin","is_new":"0","filtered_out":0,"airlineroutes":[{"carrier":"A9","carrier_name":"Georgian Airways","first_flight":null,"last_flight":"2022-04-03","common_duration":"240","route_id":"44071","is_new":"0"}]},{"first_flight":"2018-03-28","common_duration":"250","iata_from":"TBS","iata_to":"BLQ","id":44035,"city_name_en":"Bologna","is_new":"0","filtered_out":0,"airlineroutes":[{"carrier":"A9","carrier_name":"Georgian Airways","first_flight":null,"last_flight":"2022-04-03","common_duration":"250","route_id":"44035","is_new":"0"}]},{"first_flight":"2018-03-25","common_duration":"300","iata_from":"TBS","iata_to":"BRU","id":44036,"city_name_en":"Brussels","is_new":"0","filtered_out":0,"airlineroutes":[{"carrier":"A9","carrier_name":"Georgian Airways","first_flight":null,"last_flight":"2020-10-22","common_duration":"300","route_id":"44036","is_new":"0"}]},{"first_flight":"2018-02-03","common_duration":"165","iata_from":"TBS","iata_to":"OTP","id":44059,"city_name_en":"Bucharest","is_new":"0","filtered_out":0,"airlineroutes":[{"carrier":"RO","carrier_name":"TAROM","first_flight":null,"last_flight":"2021-10-30","common_duration":"165","route_id":"44059","is_new":"0"}]},{"first_flight":null,"common_duration":"185","iata_from":"TBS","iata_to":"DOH","id":44042,"city_name_en":"Doha","is_new":"0","filtered_out":0,"airlineroutes":[{"carrier":"QR","carrier_name":"Qatar Airways","first_flight":null,"last_flight":"2021-03-27","common_duration":"185","route_id":"44042","is_new":"0"}]},{"first_flight":null,"common_duration":"200","iata_from":"TBS","iata_to":"DXB","id":44043,"city_name_en":"Dubai","is_new":"0","filtered_out":0,"airlineroutes":[{"carrier":"FZ","carrier_name":"flydubai","first_flight":null,"last_flight":"2021-03-27","common_duration":"200","route_id":"44043","is_new":"0"}]},{"first_flight":"2018-09-17","common_duration":"140","iata_from":"TBS","iata_to":"IFN","id":58387,"city_name_en":"Isfahan","is_new":"0","filtered_out":0,"airlineroutes":[{"carrier":"IR","carrier_name":"Iran Air","first_flight":null,"last_flight":"2021-09-26","common_duration":"140","route_id":"58387","is_new":"0"}]},{"first_flight":null,"common_duration":"145","iata_from":"TBS","iata_to":"SAW","id":44064,"city_name_en":"Istanbul","is_new":"0","filtered_out":0,"airlineroutes":[{"carrier":"PC","carrier_name":"Pegasus","first_flight":null,"last_flight":"2020-10-24","common_duration":"150","route_id":"44064","is_new":"0"},{"carrier":"TK","carrier_name":"Turkish Airlines","first_flight":null,"last_flight":"2021-03-27","common_duration":"140","route_id":"44064","is_new":"0"}]},{"first_flight":null,"common_duration":"165","iata_from":"TBS","iata_to":"IST","id":44049,"city_name_en":"Istanbul","is_new":"0","filtered_out":0,"airlineroutes":[{"carrier":"TK","carrier_name":"Turkish Airlines","first_flight":null,"last_flight":"2021-03-27","common_duration":"165","route_id":"44049","is_new":"0"}]},{"first_flight":null,"common_duration":"180","iata_from":"TBS","iata_to":"HRK","id":54368,"city_name_en":"Kharkov","is_new":"0","filtered_out":0,"airlineroutes":[{"carrier":"PQ","carrier_name":"SkyUp Airlines","first_flight":null,"last_flight":"2021-11-01","common_duration":"180","route_id":"54368","is_new":"1"}]},{"first_flight":null,"common_duration":"180","iata_from":"TBS","iata_to":"KBP","id":44050,"city_name_en":"Kiev","is_new":"0","filtered_out":0,"airlineroutes":[{"carrier":"A9","carrier_name":"Georgian Airways","first_flight":null,"last_flight":"2020-03-27","common_duration":"160","route_id":"44050","is_new":"0"},{"carrier":"PS","carrier_name":"UIA","first_flight":null,"last_flight":"2021-03-27","common_duration":"185","route_id":"44050","is_new":"0"},{"carrier":"PQ","carrier_name":"SkyUp Airlines","first_flight":null,"last_flight":"2021-10-31","common_duration":"180","route_id":"44050","is_new":"0"},{"carrier":"YE","carrier_name":"Yan Air","first_flight":null,"last_flight":"2020-01-05","common_duration":"180","route_id":"44050","is_new":"1"}]},{"first_flight":"2018-06-11","common_duration":"160","iata_from":"TBS","iata_to":"KWI","id":44051,"city_name_en":"Kuwait","is_new":"0","filtered_out":0,"airlineroutes":[{"carrier":"J9","carrier_name":"Jazeera Airways","first_flight":null,"last_flight":"2021-09-20","common_duration":"160","route_id":"44051","is_new":"0"}]},{"first_flight":"2019-12-14","common_duration":"330","iata_from":"TBS","iata_to":"LGW","id":44054,"city_name_en":"London","is_new":"0","filtered_out":0,"airlineroutes":[{"carrier":"A9","carrier_name":"Georgian Airways","first_flight":null,"last_flight":"2022-04-08","common_duration":"330","route_id":"44054","is_new":"0"}]},{"first_flight":null,"common_duration":"180","iata_from":"TBS","iata_to":"MSQ","id":44056,"city_name_en":"Minsk","is_new":"0","filtered_out":0,"airlineroutes":[{"carrier":"B2","carrier_name":"Belavia","first_flight":null,"last_flight":"2020-10-25","common_duration":"180","route_id":"44056","is_new":"0"}]},{"first_flight":null,"common_duration":"215","iata_from":"TBS","iata_to":"VKO","id":44076,"city_name_en":"Moscow","is_new":"0","filtered_out":0,"airlineroutes":[{"carrier":"A9","carrier_name":"Georgian Airways","first_flight":null,"last_flight":"2020-03-28","common_duration":"215","route_id":"44076","is_new":"0"}]},{"first_flight":null,"common_duration":"180","iata_from":"TBS","iata_to":"BAH","id":44033,"city_name_en":"Muharraq","is_new":"0","filtered_out":0,"airlineroutes":[{"carrier":"GF","carrier_name":"Gulf Air","first_flight":null,"last_flight":"2021-09-10","common_duration":"180","route_id":"44033","is_new":"0"}]},{"first_flight":null,"common_duration":"260","iata_from":"TBS","iata_to":"MUC","id":44057,"city_name_en":"Munich","is_new":"0","filtered_out":0,"airlineroutes":[{"carrier":"LH","carrier_name":"Lufthansa","first_flight":null,"last_flight":"2021-03-27","common_duration":"260","route_id":"44057","is_new":"0"}]},{"first_flight":"2018-03-27","common_duration":"300","iata_from":"TBS","iata_to":"CDG","id":44039,"city_name_en":"Paris","is_new":"0","filtered_out":0,"airlineroutes":[{"carrier":"A9","carrier_name":"Georgian Airways","first_flight":null,"last_flight":"2022-04-04","common_duration":"293","route_id":"44039","is_new":"0"},{"carrier":"AF","carrier_name":"Air France","first_flight":null,"last_flight":"2020-10-22","common_duration":"315","route_id":"44039","is_new":"0"}]},{"first_flight":null,"common_duration":"220","iata_from":"TBS","iata_to":"PRG","id":44061,"city_name_en":"Prague","is_new":"0","filtered_out":0,"airlineroutes":[{"carrier":"A9","carrier_name":"Georgian Airways","first_flight":null,"last_flight":"2022-04-04","common_duration":"220","route_id":"44061","is_new":"0"}]},{"first_flight":null,"common_duration":"205","iata_from":"TBS","iata_to":"RIX","id":44062,"city_name_en":"Riga","is_new":"0","filtered_out":0,"airlineroutes":[{"carrier":"BT","carrier_name":"Air Baltic","first_flight":null,"last_flight":"2022-11-06","common_duration":"205","route_id":"44062","is_new":"0"}]},{"first_flight":null,"common_duration":"190","iata_from":"TBS","iata_to":"SHJ","id":44066,"city_name_en":"Sharjah","is_new":"0","filtered_out":0,"airlineroutes":[{"carrier":"G9","carrier_name":"Air Arabia","first_flight":null,"last_flight":"2021-10-21","common_duration":"190","route_id":"44066","is_new":"0"}]},{"first_flight":null,"common_duration":"210","iata_from":"TBS","iata_to":"SSH","id":44068,"city_name_en":"Sharm El-Sheikh","is_new":"0","filtered_out":0,"airlineroutes":[{"carrier":"SM","carrier_name":"Air Cairo","first_flight":null,"last_flight":"2020-12-19","common_duration":"210","route_id":"44068","is_new":"0"}]},{"first_flight":null,"common_duration":"180","iata_from":"TBS","iata_to":"TAS","id":66129,"city_name_en":"Tashkent","is_new":"0","filtered_out":0,"airlineroutes":[{"carrier":"HY","carrier_name":"Uzbekistan Airways","first_flight":null,"last_flight":"2021-04-08","common_duration":"180","route_id":"66129","is_new":"0"}]},{"first_flight":null,"common_duration":"105","iata_from":"TBS","iata_to":"IKA","id":44048,"city_name_en":"Tehran","is_new":"0","filtered_out":0,"airlineroutes":[{"carrier":"QB","carrier_name":"Qeshm Air","first_flight":null,"last_flight":"2021-10-02","common_duration":"165","route_id":"44048","is_new":"0"},{"carrier":"IR","carrier_name":"Iran Air","first_flight":null,"last_flight":"2021-10-01","common_duration":"100","route_id":"44048","is_new":"0"}]},{"first_flight":"2018-05-14","common_duration":"160","iata_from":"TBS","iata_to":"TLV","id":44072,"city_name_en":"Tel Aviv","is_new":"0","filtered_out":0,"airlineroutes":[{"carrier":"A9","carrier_name":"Georgian Airways","first_flight":null,"last_flight":"2021-11-05","common_duration":"155","route_id":"44072","is_new":"0"},{"carrier":"IZ","carrier_name":"Arkia Israeli Airlines","first_flight":"2020-05-11","last_flight":"2020-10-23","common_duration":"170","route_id":"44072","is_new":"0"},{"carrier":"LY","carrier_name":"El Al","first_flight":null,"last_flight":"2020-10-23","common_duration":"160","route_id":"44072","is_new":"0"},{"carrier":"MJ","carrier_name":"Myway Airlines","first_flight":null,"last_flight":"2021-10-30","common_duration":"255","route_id":"44072","is_new":"0"}]},{"first_flight":null,"common_duration":"195","iata_from":"TBS","iata_to":"TSE","id":44073,"city_name_en":"Tselinograd","is_new":"0","filtered_out":0,"airlineroutes":[{"carrier":"KC","carrier_name":"Air Astana","first_flight":null,"last_flight":"2021-03-26","common_duration":"195","route_id":"44073","is_new":"0"}]},{"first_flight":null,"common_duration":"285","iata_from":"TBS","iata_to":"URC","id":44074,"city_name_en":"Urumqi","is_new":"0","filtered_out":0,"airlineroutes":[{"carrier":"CZ","carrier_name":"China Southern Airlines","first_flight":null,"last_flight":"2021-03-27","common_duration":"285","route_id":"44074","is_new":"0"}]},{"first_flight":null,"common_duration":"208","iata_from":"TBS","iata_to":"VIE","id":44075,"city_name_en":"Vienna","is_new":"0","filtered_out":0,"airlineroutes":[{"carrier":"A9","carrier_name":"Georgian Airways","first_flight":null,"last_flight":"2020-10-22","common_duration":"208","route_id":"44075","is_new":"0"}]},{"first_flight":null,"common_duration":"235","iata_from":"TBS","iata_to":"WAW","id":44077,"city_name_en":"Warsaw","is_new":"0","filtered_out":0,"airlineroutes":[{"carrier":"LO","carrier_name":"LOT - Polish Airlines","first_flight":null,"last_flight":"2021-03-27","common_duration":"235","route_id":"44077","is_new":"0"}]},{"first_flight":null,"common_duration":"30","iata_from":"TBS","iata_to":"EVN","id":44044,"city_name_en":"Yerevan","is_new":"0","filtered_out":0,"airlineroutes":[{"carrier":"RM","carrier_name":"Armenia Aircompany","first_flight":null,"last_flight":"2020-12-17","common_duration":"30","route_id":"44044","is_new":"1"}]}]}]