[{"iata_from":"XCR","routes":[{"first_flight":"2018-11-03","common_duration":"170","iata_from":"XCR","iata_to":"FEZ","id":58552,"city_name_en":"Fez","is_new":"0","filtered_out":0,"airlineroutes":[{"carrier":"FR","carrier_name":"Ryanair","first_flight":null,"last_flight":"2021-10-30","common_duration":"170","route_id":"58552","is_new":"0"}]},{"first_flight":null,"common_duration":"120","iata_from":"XCR","iata_to":"MAD","id":63265,"city_name_en":"Madrid","is_new":"0","filtered_out":0,"airlineroutes":[{"carrier":"IB","carrier_name":"Iberia","first_flight":null,"last_flight":"2022-04-02","common_duration":"120","route_id":"63265","is_new":"0"}]},{"first_flight":null,"common_duration":"190","iata_from":"XCR","iata_to":"RAK","id":48717,"city_name_en":"Marrakech","is_new":"0","filtered_out":0,"airlineroutes":[{"carrier":"FR","carrier_name":"Ryanair","first_flight":null,"last_flight":"2021-11-05","common_duration":"190","route_id":"48717","is_new":"0"}]},{"first_flight":null,"common_duration":"145","iata_from":"XCR","iata_to":"OPO","id":48716,"city_name_en":"Porto","is_new":"0","filtered_out":0,"airlineroutes":[{"carrier":"FR","carrier_name":"Ryanair","first_flight":null,"last_flight":"2021-11-02","common_duration":"145","route_id":"48716","is_new":"0"}]}]}]